{
    "asset": {
        "format": "png",
        "id": "045e503089f205ef2c447f7ead34035d",
        "name": "536.png",
        "path": "file:/Users/McClain/Desktop/polyp_vis/original_png/536.png",
        "size": {
            "width": 384,
            "height": 288
        },
        "state": 2,
        "type": 1
    },
    "regions": [
        {
            "id": "yv35pPOdM",
            "type": "RECTANGLE",
            "tags": [
                "polyp"
            ],
            "boundingBox": {
                "height": 102.68636738056013,
                "width": 96.88071693448703,
                "left": 239.36588380716935,
                "top": 166.67421746293246
            },
            "points": [
                {
                    "x": 239.36588380716935,
                    "y": 166.67421746293246
                },
                {
                    "x": 336.2466007416564,
                    "y": 166.67421746293246
                },
                {
                    "x": 336.2466007416564,
                    "y": 269.3605848434926
                },
                {
                    "x": 239.36588380716935,
                    "y": 269.3605848434926
                }
            ]
        },
        {
            "id": "GnjYfM4mg",
            "type": "RECTANGLE",
            "tags": [
                "polyp"
            ],
            "boundingBox": {
                "height": 147.51956342668862,
                "width": 115.83930778739185,
                "left": 63.087144622991346,
                "top": 109.79221581548599
            },
            "points": [
                {
                    "x": 63.087144622991346,
                    "y": 109.79221581548599
                },
                {
                    "x": 178.9264524103832,
                    "y": 109.79221581548599
                },
                {
                    "x": 178.9264524103832,
                    "y": 257.3117792421746
                },
                {
                    "x": 63.087144622991346,
                    "y": 257.3117792421746
                }
            ]
        }
    ],
    "version": "2.1.0"
}