{
    "asset": {
        "format": "png",
        "id": "60cb7f31f4e8c151da59c5f41ac7ee39",
        "name": "256.png",
        "path": "file:/Users/McClain/Desktop/polyp_vis/original_png/256.png",
        "size": {
            "width": 384,
            "height": 288
        },
        "state": 2,
        "type": 1
    },
    "regions": [
        {
            "id": "_OkUWLvRG",
            "type": "RECTANGLE",
            "tags": [
                "polyp"
            ],
            "boundingBox": {
                "height": 152.6033772652389,
                "width": 233.50309023485786,
                "left": 41.147095179233624,
                "top": 115.87314662273477
            },
            "points": [
                {
                    "x": 41.147095179233624,
                    "y": 115.87314662273477
                },
                {
                    "x": 274.6501854140915,
                    "y": 115.87314662273477
                },
                {
                    "x": 274.6501854140915,
                    "y": 268.47652388797366
                },
                {
                    "x": 41.147095179233624,
                    "y": 268.47652388797366
                }
            ]
        }
    ],
    "version": "2.1.0"
}