{
    "asset": {
        "format": "png",
        "id": "6326316691cba6dd6707535590adc020",
        "name": "200.png",
        "path": "file:/Users/McClain/Desktop/polyp_vis/original_png/200.png",
        "size": {
            "width": 384,
            "height": 288
        },
        "state": 2,
        "type": 1
    },
    "regions": [
        {
            "id": "6P9m2Aql6",
            "type": "RECTANGLE",
            "tags": [
                "polyp"
            ],
            "boundingBox": {
                "height": 100.83484349258649,
                "width": 128.1007416563659,
                "left": 128.3213844252163,
                "top": 131.36923393739704
            },
            "points": [
                {
                    "x": 128.3213844252163,
                    "y": 131.36923393739704
                },
                {
                    "x": 256.42212608158223,
                    "y": 131.36923393739704
                },
                {
                    "x": 256.42212608158223,
                    "y": 232.20407742998353
                },
                {
                    "x": 128.3213844252163,
                    "y": 232.20407742998353
                }
            ]
        }
    ],
    "version": "2.1.0"
}