{
    "asset": {
        "format": "png",
        "id": "68b10980816101a38752da80d0e3e4c7",
        "name": "609.png",
        "path": "file:/Users/McClain/Desktop/polyp_vis/original_png/609.png",
        "size": {
            "width": 384,
            "height": 288
        },
        "state": 2,
        "type": 1
    },
    "regions": [
        {
            "id": "Cf6TaKB9R",
            "type": "RECTANGLE",
            "tags": [
                "polyp"
            ],
            "boundingBox": {
                "height": 86.56239770867431,
                "width": 107.08895705521472,
                "left": 145.46503067484662,
                "top": 151.73322422258593
            },
            "points": [
                {
                    "x": 145.46503067484662,
                    "y": 151.73322422258593
                },
                {
                    "x": 252.55398773006135,
                    "y": 151.73322422258593
                },
                {
                    "x": 252.55398773006135,
                    "y": 238.29562193126023
                },
                {
                    "x": 145.46503067484662,
                    "y": 238.29562193126023
                }
            ]
        }
    ],
    "version": "2.1.0"
}