{
    "asset": {
        "format": "png",
        "id": "9ea5235f2692b7e7292656a240b5ae7e",
        "name": "126.png",
        "path": "file:/Users/McClain/Desktop/polyp_vis/original_png/126.png",
        "size": {
            "width": 384,
            "height": 288
        },
        "state": 2,
        "type": 1
    },
    "regions": [
        {
            "id": "AWp7LLO3M",
            "type": "RECTANGLE",
            "tags": [
                "polyp"
            ],
            "boundingBox": {
                "height": 171.2909802306425,
                "width": 102.7601977750309,
                "left": 244.22002472187887,
                "top": 29.01832784184514
            },
            "points": [
                {
                    "x": 244.22002472187887,
                    "y": 29.01832784184514
                },
                {
                    "x": 346.9802224969098,
                    "y": 29.01832784184514
                },
                {
                    "x": 346.9802224969098,
                    "y": 200.30930807248765
                },
                {
                    "x": 244.22002472187887,
                    "y": 200.30930807248765
                }
            ]
        }
    ],
    "version": "2.1.0"
}