{
    "asset": {
        "format": "png",
        "id": "a7944c9c9b45afd2520e1d51f3f3ced0",
        "name": "562.png",
        "path": "file:/Users/McClain/Desktop/polyp_vis/original_png/562.png",
        "size": {
            "width": 384,
            "height": 288
        },
        "state": 2,
        "type": 1
    },
    "regions": [
        {
            "id": "1N1KpP_kh",
            "type": "RECTANGLE",
            "tags": [
                "polyp"
            ],
            "boundingBox": {
                "height": 67.83546128500824,
                "width": 78.2317676143387,
                "left": 181.81705809641534,
                "top": 114.12726523887973
            },
            "points": [
                {
                    "x": 181.81705809641534,
                    "y": 114.12726523887973
                },
                {
                    "x": 260.04882571075404,
                    "y": 114.12726523887973
                },
                {
                    "x": 260.04882571075404,
                    "y": 181.96272652388797
                },
                {
                    "x": 181.81705809641534,
                    "y": 181.96272652388797
                }
            ]
        },
        {
            "id": "_Hu9vTYel",
            "type": "RECTANGLE",
            "tags": [
                "polyp"
            ],
            "boundingBox": {
                "height": 109.61058484349259,
                "width": 111.33189122373301,
                "left": 46.35537700865266,
                "top": 147.4361614497529
            },
            "points": [
                {
                    "x": 46.35537700865266,
                    "y": 147.4361614497529
                },
                {
                    "x": 157.68726823238566,
                    "y": 147.4361614497529
                },
                {
                    "x": 157.68726823238566,
                    "y": 257.04674629324546
                },
                {
                    "x": 46.35537700865266,
                    "y": 257.04674629324546
                }
            ]
        }
    ],
    "version": "2.1.0"
}