{
    "asset": {
        "format": "png",
        "id": "b682aa83a21a265e1deb35bde5b0a399",
        "name": "160.png",
        "path": "file:/Users/McClain/Desktop/polyp_vis/original_png/160.png",
        "size": {
            "width": 384,
            "height": 288
        },
        "state": 2,
        "type": 1
    },
    "regions": [
        {
            "id": "BixZzFLpG",
            "type": "RECTANGLE",
            "tags": [
                "polyp"
            ],
            "boundingBox": {
                "height": 139.12747116968697,
                "width": 108.66007416563659,
                "left": 110.00432632880099,
                "top": 15.284802306425041
            },
            "points": [
                {
                    "x": 110.00432632880099,
                    "y": 15.284802306425041
                },
                {
                    "x": 218.6644004944376,
                    "y": 15.284802306425041
                },
                {
                    "x": 218.6644004944376,
                    "y": 154.41227347611203
                },
                {
                    "x": 110.00432632880099,
                    "y": 154.41227347611203
                }
            ]
        }
    ],
    "version": "2.1.0"
}