{
    "asset": {
        "format": "png",
        "id": "fdcd8854325641d5f27c1532b271e494",
        "name": "505.png",
        "path": "file:/Users/McClain/Desktop/polyp_vis/original_png/505.png",
        "size": {
            "width": 384,
            "height": 288
        },
        "state": 2,
        "type": 1
    },
    "regions": [
        {
            "id": "n5OYmnFhy",
            "type": "RECTANGLE",
            "tags": [
                "polyp"
            ],
            "boundingBox": {
                "height": 177.76668039538714,
                "width": 151.066131025958,
                "left": 70.73918417799753,
                "top": 56.91350906095552
            },
            "points": [
                {
                    "x": 70.73918417799753,
                    "y": 56.91350906095552
                },
                {
                    "x": 221.8053152039555,
                    "y": 56.91350906095552
                },
                {
                    "x": 221.8053152039555,
                    "y": 234.68018945634267
                },
                {
                    "x": 70.73918417799753,
                    "y": 234.68018945634267
                }
            ]
        }
    ],
    "version": "2.1.0"
}