<annotation verified="yes">
    <folder>Annotation</folder>
    <filename>409.png</filename>
    <path>yolo_original-PascalVOC-export/Annotations/409.png</path>
    <source>
        <database>Unknown</database>
    </source>
    <size>
        <width>384</width>
        <height>288</height>
        <depth>3</depth>
    </size>
    <segmented>0</segmented>
    <object>
    <name>polyp</name>
    <pose>Unspecified</pose>
    <truncated>0</truncated>
    <difficult>0</difficult>
    <bndbox>
        <xmin>48.02966625463535</xmin>
        <ymin>17.67009884678748</ymin>
        <xmax>295.8355995055624</xmax>
        <ymax>177.49979406919275</ymax>
    </bndbox>
</object>
</annotation>
