{
    "asset": {
        "format": "jpg",
        "id": "444b6d9a96e27ec9435c5f7fb6510225",
        "name": "132.jpg",
        "path": "file:/Users/McClain/Desktop/polyp_vis/data_polyps/train/polyps/132.jpg",
        "size": {
            "width": 64,
            "height": 70
        },
        "state": 2,
        "type": 1
    },
    "regions": [
        {
            "id": "naRqMye9E",
            "type": "RECTANGLE",
            "tags": [
                "polyp"
            ],
            "boundingBox": {
                "height": 67.88320887888706,
                "width": 62.29114490161002,
                "left": 1.7088550983899822,
                "top": 1.112546031096563
            },
            "points": [
                {
                    "x": 1.7088550983899822,
                    "y": 1.112546031096563
                },
                {
                    "x": 64,
                    "y": 1.112546031096563
                },
                {
                    "x": 64,
                    "y": 68.99575490998363
                },
                {
                    "x": 1.7088550983899822,
                    "y": 68.99575490998363
                }
            ]
        }
    ],
    "version": "2.1.0"
}